nova/__init__.py
nova/api/__init__.py
nova/api/client.py
nova/api/mutations.py
nova/api/queries.py
nova/clients/__init__.py
nova/clients/alpaca.py
nova/clients/binance.py
nova/clients/bybit.py
nova/clients/clients.py
nova/clients/coinbase.py
nova/clients/cryptocom.py
nova/clients/ftx.py
nova/clients/gate.py
nova/clients/gemini.py
nova/clients/huobi.py
nova/clients/kraken.py
nova/clients/kucoin.py
nova/clients/oanda.py
nova/clients/okx.py
nova/data/__init__.py
nova/data/discord.py
nova/data/orderbook.py
nova/data/reddit.py
nova/data/telegram.py
nova/random/__init__.py
nova/random/backtest.py
nova/random/bot.py
nova/utils/__init__.py
nova/utils/backtest.py
nova/utils/bot.py
nova/utils/constant.py
nova/utils/helpers.py
nova/utils/telegram.py
test/__init__.py
test/__pycache__/__init__.cpython-310.pyc
test/api/__init__.py
test/api/test_bots.py
test/api/test_pairs.py
test/api/test_positions.py
test/api/test_strategies.py
test/backtest/__init__.py
test/backtest/test_get_list_pair.py
test/bot/__init__.py
test/bot/test_computed_profit.py
test/bot/test_entering_positions.py
test/bot/test_exiting_positions.py
test/bot/test_get_position_size.py
test/bot/test_production_run.py
test/bot/test_security_close_all_positions.py
test/bot/test_verify_positions.py
test/clients/__init__.py
test/clients/test_cancel_order.py
test/clients/test_enter_limit_then_market.py
test/clients/test_enter_market_order.py
test/clients/test_exit_limit_then_market.py
test/clients/test_exit_market_order.py
test/clients/test_format_data.py
test/clients/test_get_actual_positions.py
test/clients/test_get_earliest_timestamp.py
test/clients/test_get_historical_data.py
test/clients/test_get_last_price.py
test/clients/test_get_order.py
test/clients/test_get_order_book.py
test/clients/test_get_order_trades.py
test/clients/test_get_pairs_info.py
test/clients/test_get_prod_data.py
test/clients/test_get_server_time.py
test/clients/test_get_token_balance.py
test/clients/test_get_tp_sl_state.py
novalabs-1.2.75.dist-info/LICENSE
novalabs-1.2.75.dist-info/METADATA
novalabs-1.2.75.dist-info/WHEEL
novalabs-1.2.75.dist-info/top_level.txt
novalabs-1.2.75.dist-info/RECORD
