Metadata-Version: 2.1
Name: novalabs
Version: 1.2.75
Summary: Wrappers around Nova Labs utilities focused on safety and testability
Home-page: https://github.com/Nova-DevTeam/nova-python
Author: Nova Labs
Author-email: devteam@novalabs.ai
License: UNKNOWN
Platform: UNKNOWN
Classifier: Programming Language :: Python :: 3
Classifier: License :: OSI Approved :: MIT License
Classifier: Operating System :: OS Independent
